framewise/__init__.py
framewise/cli.py
framewise/core/__init__.py
framewise/core/frame_extractor.py
framewise/core/transcript_extractor.py
framewise/embeddings/__init__.py
framewise/embeddings/embedder.py
framewise/retrieval/__init__.py
framewise/retrieval/qa_system.py
framewise/retrieval/vector_store.py
framewise/utils/__init__.py
framewise/utils/transcript_corrections.py
framewise-0.1.3.dist-info/LICENSE
framewise-0.1.3.dist-info/METADATA
framewise-0.1.3.dist-info/WHEEL
framewise-0.1.3.dist-info/entry_points.txt
framewise-0.1.3.dist-info/RECORD
