Metadata-Version: 2.3
Name: framewise
Version: 0.1.3
Summary: AI-powered video tutorial assistant with intelligent frame extraction and multimodal RAG
License: MIT
Keywords: video,rag,ai,tutorials,multimodal,embeddings,llm,whisper,clip,langchain
Author: Mohammad Esmaeili
Author-email: mimonachi@gmail.com
Requires-Python: >=3.9,<3.14
Classifier: Development Status :: 3 - Alpha
Classifier: Intended Audience :: Developers
Classifier: Intended Audience :: Education
Classifier: Intended Audience :: Science/Research
Classifier: License :: OSI Approved :: MIT License
Classifier: Operating System :: OS Independent
Classifier: Programming Language :: Python :: 3
Classifier: Programming Language :: Python :: 3.9
Classifier: Programming Language :: Python :: 3.10
Classifier: Programming Language :: Python :: 3.11
Classifier: Programming Language :: Python :: 3.12
Classifier: Programming Language :: Python :: 3.13
Classifier: Topic :: Multimedia :: Video
Classifier: Topic :: Scientific/Engineering :: Artificial Intelligence
Classifier: Topic :: Software Development :: Libraries :: Python Modules
Classifier: Topic :: Text Processing :: Linguistic
Provides-Extra: all
Provides-Extra: llm
Requires-Dist: Pillow (>=10.0.0,<11.0.0)
Requires-Dist: anthropic (>=0.39.0,<0.40.0) ; extra == "llm" or extra == "all"
Requires-Dist: lancedb (>=0.3.0,<0.4.0)
Requires-Dist: langchain (>=0.3.0,<0.4.0) ; extra == "llm" or extra == "all"
Requires-Dist: langchain-anthropic (>=0.3.0,<0.4.0) ; extra == "llm" or extra == "all"
Requires-Dist: loguru (>=0.7.0,<0.8.0)
Requires-Dist: numpy (>=1.24.0,<2.0.0)
Requires-Dist: openai-whisper (>=20231117,<20231118)
Requires-Dist: opencv-python (>=4.8.0,<5.0.0)
Requires-Dist: python-dotenv (>=1.0.0,<2.0.0) ; extra == "llm" or extra == "all"
Requires-Dist: sentence-transformers (>=2.2.2,<3.0.0)
Requires-Dist: transformers (>=4.35.0,<5.0.0)
Project-URL: Documentation, https://github.com/mesmaeili73/framewise#readme
Project-URL: Homepage, https://github.com/mesmaeili73/framewise
Project-URL: Repository, https://github.com/mesmaeili73/framewise
